tredge/__init__.py
tredge/core.py
tredge-0.0.3.dist-info/LICENSE
tredge-0.0.3.dist-info/METADATA
tredge-0.0.3.dist-info/WHEEL
tredge-0.0.3.dist-info/top_level.txt
tredge-0.0.3.dist-info/RECORD
