Metadata-Version: 2.1
Name: tredge
Version: 0.0.3
Summary: Python module for finding transitive edges in a directed acyclic graph
Home-page: https://github.com/pgolo/tredge
Author: Pavel Golovatenko-Abramov
Author-email: p.golovatenko@gmail.com
License: MIT
Platform: any
Classifier: Development Status :: 3 - Alpha
Classifier: Intended Audience :: Developers
Classifier: Topic :: Software Development :: Libraries :: Python Modules
Classifier: Topic :: Scientific/Engineering
Classifier: Programming Language :: Python :: 3.6
Classifier: Programming Language :: Python :: 3.7
Classifier: Programming Language :: Python :: 3.8
Classifier: License :: OSI Approved :: MIT License
Classifier: Operating System :: OS Independent
Requires-Python: >=3.6
